chatbot_test_framework/__init__.py
chatbot_test_framework/cli.py
chatbot_test_framework/default_configs/bedrock_config.yaml
chatbot_test_framework/default_configs/gemini_config.yaml
chatbot_test_framework/default_configs/prompts.py
chatbot_test_framework/default_configs/sonnet_config.yaml
chatbot_test_framework/default_configs/test_config.yaml
chatbot_test_framework/framework/config.py
chatbot_test_framework/framework/runner.py
chatbot_test_framework/framework/clients/api_client.py
chatbot_test_framework/framework/clients/base.py
chatbot_test_framework/framework/core/trace.py
chatbot_test_framework/framework/evaluators/latency.py
chatbot_test_framework/framework/evaluators/llm_providers.py
chatbot_test_framework/framework/evaluators/performance.py
chatbot_test_framework/framework/recorders/__init__.py
chatbot_test_framework/framework/recorders/base.py
chatbot_test_framework/framework/recorders/dynamodb_recorder.py
chatbot_test_framework/framework/recorders/local_json_recorder.py
chatbot_test_framework/framework/reporting/__init__.py
chatbot_test_framework/framework/reporting/html_generator.py
chatbot_test_framework-0.1.18.dist-info/METADATA
chatbot_test_framework-0.1.18.dist-info/WHEEL
chatbot_test_framework-0.1.18.dist-info/entry_points.txt
chatbot_test_framework-0.1.18.dist-info/top_level.txt
chatbot_test_framework-0.1.18.dist-info/RECORD
